LICENSE
README.md
causy/__init__.py
causy/causal_discovery/__init__.py
causy/causal_discovery/constraint/__init__.py
causy/causal_discovery/constraint/algorithms/__init__.py
causy/causal_discovery/constraint/algorithms/fci.py
causy/causal_discovery/constraint/algorithms/pc.py
causy/causal_discovery/constraint/independence_tests/__init__.py
causy/causal_discovery/constraint/independence_tests/common.py
causy/causal_discovery/constraint/orientation_rules/__init__.py
causy/causal_discovery/constraint/orientation_rules/fci.py
causy/causal_discovery/constraint/orientation_rules/pc.py
causy/causal_effect_estimation/multivariate_regression.py
causy/cli.py
causy/common_pipeline_steps/__init__.py
causy/common_pipeline_steps/calculation.py
causy/common_pipeline_steps/exit_conditions.py
causy/common_pipeline_steps/logic.py
causy/common_pipeline_steps/placeholder.py
causy/contrib/graph_ui.py
causy/data_loader.py
causy/edge_types.py
causy/generators.py
causy/graph.py
causy/graph_model.py
causy/graph_utils.py
causy/interfaces.py
causy/math_utils.py
causy/models.py
causy/sample_generator.py
causy/serialization.py
causy/static/android-chrome-192x192.png
causy/static/android-chrome-512x512.png
causy/static/apple-touch-icon.png
causy/static/assets/computing mouse-443e86cd.png
causy/static/assets/index-44a08037.js
causy/static/assets/index-b93acae3.js
causy/static/assets/index-efce78a3.css
causy/static/assets/prism-97f28b0c.js
causy/static/assets/style-8961fb08.css
causy/static/assets/vueflow-3647b393.css
causy/static/causy-500.png
causy/static/favicon-16x16.png
causy/static/favicon-32x32.png
causy/static/favicon.ico
causy/static/index.html
causy/ui/__init__.py
causy/ui/cli.py
causy/ui/models.py
causy/ui/server.py
causy/variables.py
causy/workspaces/__init__.py
causy/workspaces/cli.py
causy/workspaces/models.py
causy/workspaces/templates/dataloader.py.tpl
causy/workspaces/templates/pipeline.py.tpl
pyproject.toml
causy-0.1.47.dist-info/LICENSE
causy-0.1.47.dist-info/METADATA
causy-0.1.47.dist-info/WHEEL
causy-0.1.47.dist-info/entry_points.txt
causy-0.1.47.dist-info/RECORD
