Metadata-Version: 2.1
Name: causy
Version: 0.1.47
Summary: Causal discovery made easy.
License: MIT
Author: Sofia Faltenbacher
Author-email: faltenbacher.sofia@gmail.com
Requires-Python: >=3.10,<4.0
Classifier: License :: OSI Approved :: MIT License
Classifier: Programming Language :: Python :: 3
Classifier: Programming Language :: Python :: 3.10
Classifier: Programming Language :: Python :: 3.11
Classifier: Programming Language :: Python :: 3.12
Classifier: Programming Language :: Python :: 3.13
Requires-Dist: click (>=8.1.7,<9.0.0)
Requires-Dist: fastapi (>=0.112.0,<0.113.0)
Requires-Dist: httpx (>=0.27.0,<0.28.0)
Requires-Dist: jinja2 (>=3.1.4,<4.0.0)
Requires-Dist: markdown (>=3.6,<4.0)
Requires-Dist: pydantic-yaml (>=1.2.1,<2.0.0)
Requires-Dist: pyyaml (>=6.0.1,<7.0.0)
Requires-Dist: questionary (>=2.0.1,<3.0.0)
Requires-Dist: scipy (>=1.14,<2.0)
Requires-Dist: srsly (>=2.4.8,<3.0.0)
Requires-Dist: torch (>=2.4,<3.0)
Requires-Dist: typer[all] (>=0.12.3,<0.13.0)
Requires-Dist: uvicorn (>=0.30.5,<0.31.0)
